opentrons_json/__init__.py
opentrons_json/commands.py
opentrons_json/plates.py
opentrons_json/transfer.py
opentrons_json-0.0.2.dist-info/METADATA
opentrons_json-0.0.2.dist-info/WHEEL
opentrons_json-0.0.2.dist-info/top_level.txt
opentrons_json-0.0.2.dist-info/RECORD
