Metadata-Version: 2.1
Name: opentrons-json
Version: 0.0.2
Summary: A library that makes generating opentrons_json protocols easier
Home-page: UNKNOWN
Author: Keoni Gandall
Author-email: koeng101@gmail.com
License: UNKNOWN
Platform: UNKNOWN
Classifier: Programming Language :: Python :: 3
Classifier: License :: OSI Approved :: MIT License
Classifier: Operating System :: OS Independent
